reactive_platform-0.3.0-py3.7-nspkg.pth
reactive/platform/__init__.py
reactive/platform/domain/__init__.py
reactive/platform/domain/asset.py
reactive/platform/domain/instr.py
reactive/platform/domain/market.py
reactive/platform/domain/util.py
reactive/platform/domain/venue.py
reactive/platform/feed/__init__.py
reactive/platform/feed/client.py
reactive/platform/feed/decode.py
reactive/platform/feed/feedaccept.py
reactive/platform/feed/feedrequest.py
reactive/platform/feed/feedrequestreject.py
reactive/platform/feed/handler.py
reactive/platform/feed/liquidation.py
reactive/platform/feed/mdsnapshotl2.py
reactive/platform/feed/publictrade.py
reactive/platform/rest/__init__.py
reactive/platform/rest/client.py
reactive/platform/rest/constant.py
reactive/platform/util/__init__.py
reactive/platform/util/cache.py
reactive/platform/util/error.py
reactive/platform/websocket/__init__.py
reactive/platform/websocket/client.py
reactive/platform/websocket/decode.py
reactive/platform/websocket/handler.py
reactive/platform/websocket/websocket.py
reactive_platform-0.3.0.dist-info/LICENSE
reactive_platform-0.3.0.dist-info/METADATA
reactive_platform-0.3.0.dist-info/WHEEL
reactive_platform-0.3.0.dist-info/namespace_packages.txt
reactive_platform-0.3.0.dist-info/top_level.txt
reactive_platform-0.3.0.dist-info/RECORD
