Metadata-Version: 2.1
Name: reactive-platform
Version: 0.3.0
Summary: reactive-platform: Reactive Platform Python API
Home-page: https://www.reactiveexchange.com
Author: Reactive Platform
Author-email: development@reactiveexchange.com
Maintainer: Fan Zhao
License: Apache
Project-URL: Source, https://github.com/reactivemarkets/platform-py
Project-URL: Tracker, https://github.com/reactivemarkets/platform-py/issues
Keywords: reactive platform
Platform: any
Classifier: Development Status :: 4 - Beta
Classifier: Intended Audience :: Developers
Classifier: Intended Audience :: Information Technology
Classifier: License :: OSI Approved :: Apache Software License
Classifier: Operating System :: POSIX :: Linux
Classifier: Operating System :: Microsoft :: Windows
Classifier: Operating System :: MacOS :: MacOS X
Classifier: Programming Language :: Python :: 3 :: Only
Classifier: Programming Language :: Python :: 3.7
Classifier: Programming Language :: Python :: 3.8
Classifier: Topic :: Utilities
Requires-Python: >=3.7
Requires-Dist: reactive-papi (==1.2.0)
Requires-Dist: flatbuffers (>=1.12)
Requires-Dist: pytz (==2020.1)
Requires-Dist: requests (==2.23.0)
Requires-Dist: urllib3 (<1.26,>=1.25.2)
Requires-Dist: websockets (==8.1)
Requires-Dist: numpy (>=1.15.4)
Requires-Dist: pandas (==1.0.3)
Provides-Extra: testing
Requires-Dist: reactive-papi (==1.2.0) ; extra == 'testing'
Requires-Dist: pytest ; extra == 'testing'
Requires-Dist: pytest-cov ; extra == 'testing'
Requires-Dist: flake8 ; extra == 'testing'
Requires-Dist: tox ; extra == 'testing'
Requires-Dist: numpy (>=1.15.4) ; extra == 'testing'
